swiift/__about__.py
swiift/__init__.py
swiift/py.typed
swiift/api/__init__.py
swiift/api/api.py
swiift/api/spectra.py
swiift/api/utils.py
swiift/lib/__init__.py
swiift/lib/_ph_utils.py
swiift/lib/att.py
swiift/lib/constants.py
swiift/lib/dr.py
swiift/lib/graphics.py
swiift/lib/numerical.py
swiift/lib/phase_shift.py
swiift/lib/physics.py
swiift/model/__init__.py
swiift/model/frac_handlers.py
swiift/model/model.py
swiift-0.16.3.dist-info/METADATA
swiift-0.16.3.dist-info/WHEEL
swiift-0.16.3.dist-info/licenses/LICENSE
swiift-0.16.3.dist-info/RECORD
